LICENSE
README.md
setup.py
a3c_blogpost/README.md
a3c_blogpost/a3c_cartpole.py
adversarial_text/README.md
adversarial_text/__init__.py
adversarial_text/adversarial_losses.py
adversarial_text/evaluate.py
adversarial_text/gen_data.py
adversarial_text/gen_vocab.py
adversarial_text/graphs.py
adversarial_text/graphs_test.py
adversarial_text/inputs.py
adversarial_text/layers.py
adversarial_text/pretrain.py
adversarial_text/train_classifier.py
adversarial_text/train_utils.py
adversarial_text/data/__init__.py
adversarial_text/data/data_utils.py
adversarial_text/data/data_utils_test.py
adversarial_text/data/document_generators.py
attention_ocr/README.md
attention_ocr/python/all_jobs.screenrc
attention_ocr/python/common_flags.py
attention_ocr/python/data_provider.py
attention_ocr/python/data_provider_test.py
attention_ocr/python/demo_inference.py
attention_ocr/python/demo_inference_test.py
attention_ocr/python/eval.py
attention_ocr/python/inception_preprocessing.py
attention_ocr/python/metrics.py
attention_ocr/python/metrics_test.py
attention_ocr/python/model.py
attention_ocr/python/model_export.py
attention_ocr/python/model_export_lib.py
attention_ocr/python/model_export_test.py
attention_ocr/python/model_test.py
attention_ocr/python/sequence_layers.py
attention_ocr/python/sequence_layers_test.py
attention_ocr/python/train.py
attention_ocr/python/utils.py
attention_ocr/python/datasets/__init__.py
attention_ocr/python/datasets/fsns.py
attention_ocr/python/datasets/fsns_test.py
attention_ocr/python/datasets/unittest_utils.py
attention_ocr/python/datasets/unittest_utils_test.py
attention_ocr/python/datasets/testdata/fsns/charset_size=134.txt
attention_ocr/python/datasets/testdata/fsns/download_data.py
attention_ocr/python/datasets/testdata/fsns/fsns-00000-of-00001
attention_ocr/python/datasets/testdata/fsns/links.txt
attention_ocr/python/testdata/fsns_train_00.png
attention_ocr/python/testdata/fsns_train_01.png
attention_ocr/python/testdata/fsns_train_02.png
object_detection.egg-info/PKG-INFO
object_detection.egg-info/SOURCES.txt
object_detection.egg-info/dependency_links.txt
object_detection.egg-info/requires.txt
object_detection.egg-info/top_level.txt
