Metadata-Version: 1.2
Name: custom_obj_detector
Version: 1
Summary: Custom Object Detection Setup
Home-page: UNKNOWN
License: UNKNOWN
Platform: UNKNOWN
Requires-Python: >3.6
